css/alabaster.css
css/bootstrap.css
css/furo.css
css/pydata_sphinx_theme.css
css/sphinx_book_theme.css
css/sphinx_material.css
css/sphinx_rtd_theme.css
js/download_adapter.jquery.js
js/download_adapter.js
jsphinx/__init__.py
jsphinx/cdn.py
jssphinx-1.3.4.dist-info/LICENSE
jssphinx-1.3.4.dist-info/METADATA
jssphinx-1.3.4.dist-info/WHEEL
jssphinx-1.3.4.dist-info/top_level.txt
jssphinx-1.3.4.dist-info/RECORD
