Metadata-Version: 2.1
Name: jssphinx
Version: 1.3.4
Summary: Improve developer experience
Author-email: Artur Barseghyan <artur.barseghyan@gmail.com>
License: MIT
Classifier: Development Status :: 4 - Beta
Classifier: Environment :: Web Environment
Classifier: Framework :: Sphinx :: Extension
Classifier: Framework :: Sphinx :: Theme
Classifier: Framework :: Sphinx
Classifier: Intended Audience :: Developers
Classifier: License :: OSI Approved :: MIT License
Classifier: Operating System :: OS Independent
Classifier: Programming Language :: Python :: 3
Classifier: Programming Language :: Python :: 3.10
Classifier: Programming Language :: Python :: 3.11
Classifier: Programming Language :: Python :: 3.7
Classifier: Programming Language :: Python :: 3.8
Classifier: Programming Language :: Python :: 3.9
Classifier: Programming Language :: Python
Classifier: Topic :: Documentation :: Sphinx
Classifier: Topic :: Documentation
Classifier: Topic :: Software Development :: Documentation
Classifier: Topic :: Software Development
License-File: LICENSE
Requires-Dist: sphinx
Provides-Extra: all
Requires-Dist: jssphinx[dev,test,themes] ; extra == 'all'
Provides-Extra: dev
Requires-Dist: black ; extra == 'dev'
Requires-Dist: detect-secrets ; extra == 'dev'
Requires-Dist: doc8 ; extra == 'dev'
Requires-Dist: ipython ; extra == 'dev'
Requires-Dist: isort ; extra == 'dev'
Requires-Dist: pip-tools ; extra == 'dev'
Requires-Dist: ruff ; extra == 'dev'
Requires-Dist: twine ; extra == 'dev'
Provides-Extra: test
Requires-Dist: Pillow ; extra == 'test'
Requires-Dist: faker-file ; extra == 'test'
Requires-Dist: pytest ; extra == 'test'
Requires-Dist: python-docx ; extra == 'test'
Requires-Dist: selenium ; extra == 'test'
Requires-Dist: get-chromedriver-py ; extra == 'test'
Provides-Extra: themes
Requires-Dist: furo ; extra == 'themes'
Requires-Dist: pydata-sphinx-theme ; extra == 'themes'
Requires-Dist: sphinx-book-theme ; extra == 'themes'
Requires-Dist: sphinx-bootstrap-theme ; extra == 'themes'
Requires-Dist: sphinx-material ; extra == 'themes'
Requires-Dist: sphinx-rtd-theme ; extra == 'themes'
